LICENSE.txt
setup.py
TIK_afrit/AFRI.py
TIK_afrit/Arg.py
TIK_afrit/Bogus.py
TIK_afrit/OS.py
TIK_afrit/S_X.py
TIK_afrit/Taiwn.py
TIK_afrit/__init__.py
TIK_afrit/draver_id.py
TIK_afrit/gnarly.py
TIK_afrit/tiktok.py
tiktok_afriton.egg-info/PKG-INFO
tiktok_afriton.egg-info/SOURCES.txt
tiktok_afriton.egg-info/dependency_links.txt
tiktok_afriton.egg-info/top_level.txt