Metadata-Version: 2.4
Name: tiktok-afriton
Version: 0.2
Summary: your description
Author: AFRITON
Classifier: Programming Language :: Python :: 3
Classifier: Operating System :: OS Independent
Classifier: License :: OSI Approved :: MIT License
License-File: LICENSE.txt
Dynamic: author
Dynamic: classifier
Dynamic: license-file
Dynamic: summary
